pyrsmi/__init__.py
pyrsmi/_version.py
pyrsmi/rocml.py
pyrsmi-1.0.1.dist-info/LICENSE
pyrsmi-1.0.1.dist-info/METADATA
pyrsmi-1.0.1.dist-info/WHEEL
pyrsmi-1.0.1.dist-info/top_level.txt
pyrsmi-1.0.1.dist-info/RECORD
