Metadata-Version: 2.1
Name: pyrsmi
Version: 1.0.1
Summary: Python Bindings for System Management Library for AMD GPUs
Home-page: http://www.amd.com
Author: AMD Author
License: MIT
Keywords: rocm,smi,amd,system management
Classifier: Development Status :: 3 - Alpha
Classifier: Intended Audience :: Developers
Classifier: Intended Audience :: System Administrators
Classifier: License :: OSI Approved :: MIT License
Classifier: Operating System :: POSIX :: Linux
Classifier: Programming Language :: Python :: 3
Classifier: Programming Language :: Python :: 3.6
Classifier: Programming Language :: Python :: 3.7
Classifier: Programming Language :: Python :: 3.8
Classifier: Programming Language :: Python :: 3.9
Classifier: Programming Language :: Python :: 3.10
Classifier: Topic :: Software Development :: Libraries :: Python Modules
Classifier: Topic :: System :: Hardware
Classifier: Topic :: System :: Systems Administration
Requires-Python: >=3.6
License-File: LICENSE
